foldr/__init__.py
foldr/cli.py
foldr/config.py
foldr/organizer.py
foldr-0.1.5.dist-info/licenses/LICENSE
foldr-0.1.5.dist-info/METADATA
foldr-0.1.5.dist-info/WHEEL
foldr-0.1.5.dist-info/entry_points.txt
foldr-0.1.5.dist-info/top_level.txt
foldr-0.1.5.dist-info/RECORD
