Metadata-Version: 2.4
Name: foldr
Version: 0.1.5
Summary: A safe, predictable CLI tool to organize files by extension
Author-email: Muhammad Qasim <amkassim444@gmail.com>
Project-URL: Homepage, https://github.com/Kas-sim/Foldr
Project-URL: Source Code, https://github.com/Kas-sim/Foldr
Project-URL: Bug Tracker, https://github.com/Kas-sim/Foldr/issues
Classifier: License :: OSI Approved :: MIT License
Classifier: Programming Language :: Python :: 3
Classifier: Programming Language :: Python :: 3 :: Only
Classifier: Operating System :: OS Independent
Classifier: Environment :: Console
Classifier: Topic :: Utilities
Classifier: Topic :: System :: Filesystems
Requires-Python: >=3.9
License-File: LICENSE
Requires-Dist: pyfiglet>=1.0.0
Requires-Dist: rich>=13.0.0
Dynamic: license-file
